clfutils4r/__init__.py
clfutils4r/eval_classification.py
clfutils4r/gridsearch_classification.py
clfutils4r/pretty_cm.py
clfutils4r-1.0.1.dist-info/LICENSE
clfutils4r-1.0.1.dist-info/METADATA
clfutils4r-1.0.1.dist-info/WHEEL
clfutils4r-1.0.1.dist-info/top_level.txt
clfutils4r-1.0.1.dist-info/RECORD
