Metadata-Version: 2.1
Name: clfutils4r
Version: 1.0.1
Summary: Wrapper around some basic sklearn and scikit-plot utilities for classification.
Home-page: https://github.com/rutujagurav/clfutils4r
Author: Rutuja Gurav
Author-email: Rutuja Gurav <rutujagurav100@gmail.com>
Project-URL: Homepage, https://github.com/rutujagurav/clfutils4r
Project-URL: Bug Tracker, https://github.com/rutujagurav/clfutils4r/issues
Classifier: Programming Language :: Python :: 3
Classifier: License :: OSI Approved :: MIT License
Classifier: Operating System :: OS Independent
Requires-Python: >=3.6
License-File: LICENSE
